[
	{
		"from": 628170011,
		"id": 114420
	},
	{
		"from": 112065797,
		"id": 116846
	},
	{
		"from": 628118524,
		"id": 116847
	},
	{
		"from": 104015994,
		"id": 116848
	},
	{
		"from": 628144020,
		"id": 114421
	},
	{
		"from": 628143998,
		"id": 114422
	},
	{
		"from": 126903570,
		"id": 116849
	},
	{
		"from": 628117666,
		"id": 116850
	},
	{
		"from": 137840692,
		"id": 116852
	},
	{
		"from": 628117681,
		"id": 116853
	},
	{
		"from": 28600730,
		"id": 116854
	},
	{
		"from": 628118520,
		"id": 116855
	},
	{
		"from": 628170227,
		"id": 114423
	},
	{
		"from": 628170227,
		"id": 114424
	},
	{
		"from": 628118471,
		"id": 116856
	},
	{
		"from": 168981974,
		"id": 116857
	},
	{
		"from": 263851740,
		"id": 116858
	},
	{
		"from": 360204716,
		"id": 116860
	},
	{
		"from": 176345325,
		"id": 116861
	},
	{
		"from": 357445494,
		"id": 116862
	},
	{
		"from": 628118524,
		"id": 116863
	},
	{
		"from": 165844644,
		"id": 116865
	},
	{
		"from": 418700266,
		"id": 116866
	},
	{
		"from": 628118524,
		"id": 116867
	},
	{
		"from": 628118520,
		"id": 116868
	},
	{
		"from": 628118220,
		"id": 116869
	},
	{
		"from": 628170292,
		"id": 114428
	},
	{
		"from": 628170292,
		"id": 114429
	},
	{
		"from": 628170292,
		"id": 114431
	},
	{
		"from": 628170292,
		"id": 114432
	},
	{
		"from": 628170292,
		"id": 114433
	},
	{
		"from": 628170292,
		"id": 114434
	},
	{
		"from": 628170292,
		"id": 114435
	},
	{
		"from": 628170292,
		"id": 114436
	},
	{
		"from": 628170292,
		"id": 114438
	},
	{
		"from": 628170292,
		"id": 114440
	},
	{
		"from": 628142733,
		"id": 114441
	},
	{
		"from": 628170292,
		"id": 114442
	},
	{
		"from": 628170292,
		"id": 114443
	},
	{
		"from": 628170292,
		"id": 114444
	}
]